assert_mixins/__init__.py
assert_mixins/elementary.py
assert_mixins/fs.py
assert_mixins/posix.py
assertmixins-1.0.0.dist-info/METADATA
assertmixins-1.0.0.dist-info/WHEEL
assertmixins-1.0.0.dist-info/top_level.txt
assertmixins-1.0.0.dist-info/RECORD
