Metadata-Version: 2.4
Name: AssertMixins
Version: 1.0.0
Summary: Library of testing helper mixins.
Author-email: João Jerónimo <joao.jeronimo.pro@gmail.com>
Classifier: Development Status :: 5 - Production/Stable
Requires-Python: >=3.7
